pycpg/__init__.py
pycpg/__version__.py
pycpg/choices.py
pycpg/exceptions.py
pycpg/response.py
pycpg/usercontext.py
pycpg/util.py
pycpg/clients/__init__.py
pycpg/clients/archive.py
pycpg/clients/auditlogs.py
pycpg/clients/authority.py
pycpg/clients/loginconfig.py
pycpg/clients/_archiveaccess/__init__.py
pycpg/clients/_archiveaccess/accessorfactory.py
pycpg/clients/_archiveaccess/restoremanager.py
pycpg/clients/settings/__init__.py
pycpg/clients/settings/_converters.py
pycpg/clients/settings/device_settings.py
pycpg/clients/settings/org_settings.py
pycpg/constants/__init__.py
pycpg/sdk/__init__.py
pycpg/services/__init__.py
pycpg/services/_auth.py
pycpg/services/_connection.py
pycpg/services/_keyvaluestore.py
pycpg/services/administration.py
pycpg/services/archive.py
pycpg/services/auditlogs.py
pycpg/services/devices.py
pycpg/services/legalhold.py
pycpg/services/legalholdapiclient.py
pycpg/services/orgs.py
pycpg/services/users.py
pycpg/services/util.py
pycpg/services/storage/__init__.py
pycpg/services/storage/_service_factory.py
pycpg/services/storage/archive.py
pycpg/services/storage/restore.py
pycpg/settings/__init__.py
pycpg/settings/debug.py
pycpg-1.0.4.dist-info/licenses/LICENSE.md
pycpg-1.0.4.dist-info/METADATA
pycpg-1.0.4.dist-info/WHEEL
pycpg-1.0.4.dist-info/top_level.txt
pycpg-1.0.4.dist-info/RECORD
