Metadata-Version: 2.4
Name: pycpg
Version: 1.0.4
Summary: The Official CrashPlan Python API Client
License-Expression: MIT
Project-URL: Homepage, https://github.com/CrashPlan-Labs
Project-URL: Issues, https://github.com/CrashPlan-Labs/pycpg/issues
Project-URL: Documentation, https://pycpgdocs.CrashPlan.com/
Project-URL: Repository, https://github.com/CrashPlan-Labs/pycpg
Keywords: backup,crashplan
Classifier: Development Status :: 3 - Alpha
Classifier: Natural Language :: English
Classifier: Intended Audience :: Developers
Classifier: Programming Language :: Python :: 3
Classifier: Programming Language :: Python :: 3.11
Classifier: Programming Language :: Python :: 3.12
Classifier: Programming Language :: Python :: 3.13
Classifier: Programming Language :: Python :: Implementation :: CPython
Requires-Python: >=3.11
License-File: LICENSE.md
Requires-Dist: urllib3>=2.4.0
Requires-Dist: requests>=2.32.4
Provides-Extra: docs
Requires-Dist: sphinx==8.2.3; extra == "docs"
Requires-Dist: myst-parser==4.0.1; extra == "docs"
Requires-Dist: sphinx_rtd_theme==3.0.2; extra == "docs"
Requires-Dist: docutils==0.21.2; extra == "docs"
Provides-Extra: dev
Requires-Dist: flake8==7.2.0; extra == "dev"
Requires-Dist: pytest==8.4.0; extra == "dev"
Requires-Dist: pytest-cov==6.1.1; extra == "dev"
Requires-Dist: pytest-mock==3.10.0; extra == "dev"
Requires-Dist: tox==4.25.0; extra == "dev"
Provides-Extra: all
Requires-Dist: test_self_dep[DEV,docs]; extra == "all"
Dynamic: license-file
